extensions/README.md
extensions/__init__.py
extensions/catalog/README.md
extensions/catalog/any_path.py
extensions/catalog/file_system.py
extensions/catalog/minio.py
extensions/catalog/pyproject.toml
extensions/catalog/s3.py
extensions/job_executor/README.md
extensions/job_executor/__init__.py
extensions/job_executor/emulate.py
extensions/job_executor/k8s.py
extensions/job_executor/k8s_job_spec.yaml
extensions/job_executor/local.py
extensions/job_executor/local_container.py
extensions/job_executor/pyproject.toml
extensions/nodes/README.md
extensions/nodes/__init__.py
extensions/nodes/conditional.py
extensions/nodes/fail.py
extensions/nodes/map.py
extensions/nodes/parallel.py
extensions/nodes/pyproject.toml
extensions/nodes/stub.py
extensions/nodes/success.py
extensions/nodes/task.py
extensions/pipeline_executor/README.md
extensions/pipeline_executor/__init__.py
extensions/pipeline_executor/argo.py
extensions/pipeline_executor/emulate.py
extensions/pipeline_executor/local.py
extensions/pipeline_executor/local_container.py
extensions/pipeline_executor/mocked.py
extensions/pipeline_executor/pyproject.toml
extensions/pipeline_executor/retry.py
extensions/run_log_store/README.md
extensions/run_log_store/__init__.py
extensions/run_log_store/any_path.py
extensions/run_log_store/chunked_fs.py
extensions/run_log_store/chunked_minio.py
extensions/run_log_store/file_system.py
extensions/run_log_store/generic_chunked.py
extensions/run_log_store/minio.py
extensions/run_log_store/pyproject.toml
extensions/run_log_store/db/implementation_FF.py
extensions/run_log_store/db/integration_FF.py
extensions/secrets/README.md
extensions/secrets/dotenv.py
extensions/secrets/pyproject.toml
runnable/__init__.py
runnable/catalog.py
runnable/cli.py
runnable/context.py
runnable/datastore.py
runnable/defaults.py
runnable/entrypoints.py
runnable/exceptions.py
runnable/executor.py
runnable/gantt.py
runnable/graph.py
runnable/names.py
runnable/nodes.py
runnable/parameters.py
runnable/pickler.py
runnable-1.0.0.dist-info/METADATA
runnable-1.0.0.dist-info/WHEEL
runnable-1.0.0.dist-info/entry_points.txt
runnable-1.0.0.dist-info/licenses/LICENSE
runnable-1.0.0.dist-info/RECORD
