Metadata-Version: 2.4
Name: runnable
Version: 1.0.0
Summary: Add your description here
Author-email: "Vammi, Vijay" <vijay.vammi@astrazeneca.com>
License-File: LICENSE
Requires-Python: >=3.10
Requires-Dist: cloudpathlib>=0.20.0
Requires-Dist: dill>=0.3.9
Requires-Dist: pydantic>=2.10.3
Requires-Dist: python-dotenv>=1.0.1
Requires-Dist: rich>=13.9.4
Requires-Dist: ruamel-yaml>=0.18.6
Requires-Dist: setuptools>=75.6.0
Requires-Dist: stevedore>=5.4.0
Requires-Dist: typer>=0.17.3
Provides-Extra: docker
Requires-Dist: docker>=7.1.0; extra == 'docker'
Provides-Extra: examples
Requires-Dist: pandas>=2.2.3; extra == 'examples'
Provides-Extra: examples-torch
Requires-Dist: torch>=2.7.1; extra == 'examples-torch'
Provides-Extra: k8s
Requires-Dist: kubernetes>=31.0.0; extra == 'k8s'
Provides-Extra: notebook
Requires-Dist: ploomber-engine>=0.0.33; extra == 'notebook'
Provides-Extra: s3
Requires-Dist: cloudpathlib[s3]; extra == 's3'
